serial_com/serial_com.py
serial_com-0.1.12.dist-info/METADATA
serial_com-0.1.12.dist-info/WHEEL
serial_com-0.1.12.dist-info/RECORD
