Metadata-Version: 2.4
Name: serial-com
Version: 0.1.12
Summary: 
Author: Andrey Linyushin
Author-email: 89202979894@mail.ru
Requires-Python: >=3.10
Classifier: Programming Language :: Python :: 3
Classifier: Programming Language :: Python :: 3.10
Classifier: Programming Language :: Python :: 3.11
Classifier: Programming Language :: Python :: 3.12
Classifier: Programming Language :: Python :: 3.13
Classifier: Programming Language :: Python :: 3.14
Requires-Dist: crcmod (>=1.7,<2.0)
Requires-Dist: pyserial (>=3.5,<4.0)
